format_currency/__about__.py
format_currency/__init__.py
format_currency/country.py
format_currency/format.py
format_currency/data/countries.json
format_currency-0.0.10.dist-info/METADATA
format_currency-0.0.10.dist-info/WHEEL
format_currency-0.0.10.dist-info/licenses/LICENSE.txt
format_currency-0.0.10.dist-info/RECORD
