Metadata-Version: 2.1
Name: format-currency
Version: 0.0.10
Summary: A no-frill currency formatting library.
Project-URL: Documentation, https://github.com/arifwn/format-currency#readme
Project-URL: Issues, https://github.com/arifwn/format-currency/issues
Project-URL: Source, https://github.com/arifwn/format-currency
Author-email: Arif Widi Nugroho <arif@sainsmograf.com>
License-Expression: MIT
License-File: LICENSE.txt
Classifier: Development Status :: 4 - Beta
Classifier: Programming Language :: Python
Classifier: Programming Language :: Python :: 3.7
Classifier: Programming Language :: Python :: 3.8
Classifier: Programming Language :: Python :: 3.9
Classifier: Programming Language :: Python :: 3.10
Classifier: Programming Language :: Python :: 3.11
Classifier: Programming Language :: Python :: 3.12
Classifier: Programming Language :: Python :: Implementation :: CPython
Classifier: Programming Language :: Python :: Implementation :: PyPy
Classifier: Topic :: Text Processing :: Filters
Classifier: Topic :: Utilities
Requires-Python: >=3.7
